{"data":[{"Email":"eic@resource.acs.org","First Name":"Michael K.C.","Masthead Category":"Deputy Editor","Country":"Canada","Website":"http:\/\/chemeng.uwaterloo.ca\/mtam\/","Journal Name":"ACS Sustainable Resource Management","Last Name":"Tam","Institution Name":"University of Waterloo","Masthead Disclaimer":false},{"Email":"loo-office@resource.acs.org","First Name":"Joachim","Masthead Category":"Associate Editor","Country":"Singapore","Website":"https:\/\/www3.ntu.edu.sg\/home\/joachimloo\/","Journal Name":"ACS Sustainable Resource Management","Last Name":"Loo","Institution Name":"Nanyang Technological University","Masthead Disclaimer":false},{"Email":"ferrer-office@resource.acs.org","First Name":"Ivet","Masthead Category":"Associate Editor","Country":"Spain","Website":"https:\/\/gemma.upc.edu\/en","Journal Name":"ACS Sustainable Resource Management","Last Name":"Ferrer","Institution Name":"Universitat Politecnica de Catalunya","Masthead Disclaimer":false},{"Email":"managing.editor@resource.acs.org","First Name":"Carlos","Masthead Category":"Associate Publisher","Country":"United States","Website":null,"Journal Name":"ACS Sustainable Resource Management","Last Name":"Toro","Institution Name":"American Chemical Society","Masthead Disclaimer":false},{"Email":"kamkar-office@resource.acs.org","First Name":"Milad","Masthead Category":"Topic Editor","Country":"Canada","Website":"https:\/\/uwaterloo.ca\/chemical-engineering\/profiles\/milad-kamkar","Journal Name":"ACS Sustainable Resource Management","Last Name":"Kamkar","Institution Name":"University of Waterloo","Masthead Disclaimer":false},{"Email":"eic@sustain.acs.org","First Name":"Peter","Masthead Category":"Editor-in-Chief","Country":"United Kingdom","Website":"https:\/\/www.nottingham.ac.uk\/chemistry\/people\/peter.licence","Journal Name":"ACS Sustainable Resource Management","Last Name":"Licence","Institution Name":"University of Nottingham","Masthead Disclaimer":false},{"Email":"zhangzhen@m.scnu.edu.cn","First Name":"Zhen","Masthead Category":"Early Career Board","Country":"China","Website":"http:\/\/www.dirmlab.org\/en\/Teamscientist\/64.html","Journal Name":"ACS Sustainable Resource Management","Last Name":"Zhang","Institution Name":"South China Normal University","Masthead Disclaimer":false},{"Email":"ymlam@ntu.edu.sg","First Name":"Lam Yeng","Masthead Category":"Editorial Advisory Board","Country":"Singapore","Website":"https:\/\/dr.ntu.edu.sg\/cris\/rp\/rp01069","Journal Name":"ACS Sustainable Resource Management","Last Name":"Ming","Institution Name":"Nanyang Technological University","Masthead Disclaimer":false},{"Email":"phdyu@zstu.edu.cn","First Name":"Houyong","Masthead Category":"Editorial Advisory Board","Country":"China","Website":"http:\/\/www.polymer.cn\/ss\/yuhouyong\/en\/index.html","Journal Name":"ACS Sustainable Resource Management","Last Name":"Yu","Institution Name":"Zhejiang Sci-Tech University","Masthead Disclaimer":false},{"Email":"msehc@nus.edu.sg","First Name":"Chaobin","Masthead Category":"Editorial Advisory Board","Country":"Singapore","Website":"https:\/\/cde.nus.edu.sg\/mse\/staff\/he-chaobin\/","Journal Name":"ACS Sustainable Resource Management","Last Name":"He","Institution Name":"National University of Singapore","Masthead Disclaimer":false},{"Email":"helentreichel@gmail.com","First Name":"Helen","Masthead Category":"Editorial Advisory Board","Country":"Brazil","Website":"https:\/\/www.uffs.edu.br\/pastas-ocultas\/bd\/pro-reitoria-de-gestao-de-pessoas\/pessoas\/helen-treichel","Journal Name":"ACS Sustainable Resource Management","Last Name":"Treichel","Institution Name":"Universidade Estadual de Campinas","Masthead Disclaimer":false},{"Email":"dongyeop@krict.re.kr","First Name":"Dongyeop","Masthead Category":"Early Career Board","Country":"Republic of Korea","Website":"https:\/\/www.dbpia.co.kr\/author\/authorDetail?ancId=1631609","Journal Name":"ACS Sustainable Resource Management","Last Name":"Oh","Institution Name":"Korea Research Institute of Chemical Technology","Masthead Disclaimer":false},{"Email":"sonali.das@iitb.ac.in","First Name":"Sonali","Masthead Category":"Early Career Board","Country":"India","Website":"https:\/\/www.che.iitb.ac.in\/index.php\/faculty\/sonali-das","Journal Name":"ACS Sustainable Resource Management","Last Name":"Das","Institution Name":"Indian Institute of Technology Bombay","Masthead Disclaimer":false},{"Email":"m.sain@utoronto.ca","First Name":"Mohini","Masthead Category":"Editorial Advisory Board","Country":"Canada","Website":"https:\/\/www.mie.utoronto.ca\/faculty_staff\/msain\/","Journal Name":"ACS Sustainable Resource Management","Last Name":"Sain","Institution Name":"University of Toronto","Masthead Disclaimer":false},{"Email":"agi@imperial.ac.uk","First Name":"Agnieszka","Masthead Category":"Early Career Board","Country":"United Kingdom","Website":"https:\/\/www.imperial.ac.uk\/people\/agi","Journal Name":"ACS Sustainable Resource Management","Last Name":"Brandt-Talbot","Institution Name":"Imperial College London","Masthead Disclaimer":false},{"Email":"glvidal@udec.cl","First Name":"Gladys","Masthead Category":"Editorial Advisory Board","Country":"Chile","Website":"https:\/\/www.crhiam.cl\/en\/equipo\/gladys-vidal\/","Journal Name":"ACS Sustainable Resource Management","Last Name":"Vidal","Institution Name":"Universidad de Concepción","Masthead Disclaimer":false},{"Email":"onghc@sunway.edu.my","First Name":"Hwai Chyuan","Masthead Category":"Editorial Advisory Board","Country":"Taiwan","Website":"https:\/\/profiles.uts.edu.au\/HwaiChyuan.Ong","Journal Name":"ACS Sustainable Resource Management","Last Name":"Ong","Institution Name":"National Yunlin University of Science and Technology","Masthead Disclaimer":false},{"Email":"reynardtang@csu.edu.cn","First Name":"Juntao","Masthead Category":"Early Career Board","Country":"China","Website":"https:\/\/en.csu.edu.cn\/Schools\/schools2\/Chemistry_and_Chemical_ Engineering\/Faculty.htm","Journal Name":"ACS Sustainable Resource Management","Last Name":"Tang","Institution Name":"Central South University","Masthead Disclaimer":false},{"Email":"erlantz.liizundia@ehu.eus","First Name":"Erlantz","Masthead Category":"Early Career Board","Country":"Spain","Website":"https:\/\/www.ehu.eus\/en\/web\/lifecyclethinking\/erlantz-lizundia","Journal Name":"ACS Sustainable Resource Management","Last Name":"Lizundia","Institution Name":"University of the Basque Country","Masthead Disclaimer":false},{"Email":"mmisra@uoguelph.ca","First Name":"Manjusri","Masthead Category":"Editorial Advisory Board","Country":"Canada","Website":"https:\/\/www.uoguelph.ca\/engineering\/people\/manjusri-misra-phd","Journal Name":"ACS Sustainable Resource Management","Last Name":"Misra","Institution Name":"University of Guelph","Masthead Disclaimer":false},{"Email":"svarjani@cityu.edu.hk","First Name":"Sunita","Masthead Category":"Editorial Advisory Board","Country":"Hong Kong","Website":"https:\/\/scholars.cityu.edu.hk\/en\/persons\/sunita-varjani(f3620dfe-189e-4f07-9e35-fa31263f1455).html","Journal Name":"ACS Sustainable Resource Management","Last Name":"Varjani","Institution Name":"City University of Hong Kong","Masthead Disclaimer":false},{"Email":"kvg@kt.dtu.dk","First Name":"Krist","Masthead Category":"Editorial Advisory Board","Country":"Denmark","Website":"http:\/\/www.kt.dtu.dk\/english\/research\/prosys","Journal Name":"ACS Sustainable Resource Management","Last Name":"Gernaey","Institution Name":"Technical University of Denmark","Masthead Disclaimer":false},{"Email":"pradeep-office@resource.acs.org","First Name":"Thalappil","Masthead Category":"Associate Editor","Country":"India","Website":"https:\/\/pradeepresearch.org\/our-team\/t-pradeep\/","Journal Name":"ACS Sustainable Resource Management","Last Name":"Pradeep","Institution Name":"Indian Institute of Technology Madras","Masthead Disclaimer":false},{"Email":"jun.huang@sydney.edu.au","First Name":"Jun","Masthead Category":"Editorial Advisory Board","Country":"Australia","Website":"https:\/\/junhuanggroup.wixsite.com\/huang-group","Journal Name":"ACS Sustainable Resource Management","Last Name":"Huang","Institution Name":"The University of Sydney","Masthead Disclaimer":false},{"Email":"mcclements@foodsci.umass.edu","First Name":"David Julian","Masthead Category":"Editorial Advisory Board","Country":"United States","Website":"https:\/\/www.umass.edu\/food-science\/faculty\/d-julian-mcclements","Journal Name":"ACS Sustainable Resource Management","Last Name":"McClements","Institution Name":"University of Massachusetts Amherst","Masthead Disclaimer":false},{"Email":"dsanin@metu.edu.tr","First Name":"Dilek","Masthead Category":"Editorial Advisory Board","Country":"Turkey","Website":"https:\/\/enve.metu.edu.tr\/en\/sanin\/","Journal Name":"ACS Sustainable Resource Management","Last Name":"Sanin","Institution Name":"Middle East Technical University","Masthead Disclaimer":false},{"Email":"nomcebom@dut.ac.za","First Name":"Nomcebo H.","Masthead Category":"Early Career Board","Country":"South Africa","Website":"https:\/\/www.dut.ac.za\/council_member\/dr-nomcebo-mthombeni\/","Journal Name":"ACS Sustainable Resource Management","Last Name":"Mthombeni","Institution Name":"Durban University of Technology","Masthead Disclaimer":false},{"Email":"darling@anl.gov","First Name":"Seth B.","Masthead Category":"Editorial Advisory Board","Country":"United States","Website":"https:\/\/pme.uchicago.edu\/fellows\/people\/seth-darling","Journal Name":"ACS Sustainable Resource Management","Last Name":"Darling","Institution Name":"Argonne National Laboratory","Masthead Disclaimer":false},{"Email":"pauloke.show@ku.ac.ae","First Name":"Pau Loke","Masthead Category":"Editorial Advisory Board","Country":"United Arab Emirates","Website":"https:\/\/www.ku.ac.ae\/college-people\/pau-loke-show","Journal Name":"ACS Sustainable Resource Management","Last Name":"Show","Institution Name":"Khalifa University","Masthead Disclaimer":false},{"Email":"gdemirer@caltech.edu","First Name":"Gözde S.","Masthead Category":"Early Career Board","Country":"United States","Website":"https:\/\/www.demirerlab.com\/","Journal Name":"ACS Sustainable Resource Management","Last Name":"Demirer","Institution Name":"California Institute of Technology","Masthead Disclaimer":false},{"Email":"mabhaudhi@ukzn.ac.za","First Name":"Tafadzwanashe","Masthead Category":"Editorial Advisory Board","Country":"South Africa","Website":"https:\/\/saees.ukzn.ac.za\/tafadzwa-mabhaudhi\/","Journal Name":"ACS Sustainable Resource Management","Last Name":"Mabhaudhi","Institution Name":"University of KwaZulu-Natal","Masthead Disclaimer":false},{"Email":"cigdem.eskicioglu@ubc.ca","First Name":"Cigdem","Masthead Category":"Editorial Advisory Board","Country":"Canada","Website":"https:\/\/bioreactortechgroup.ok.ubc.ca\/","Journal Name":"ACS Sustainable Resource Management","Last Name":"Eskicioglu","Institution Name":"The University of British Columbia","Masthead Disclaimer":false},{"Email":"yuanzhi.tang@eas.gatech.edu","First Name":"Yuanzhi","Masthead Category":"Editorial Advisory Board","Country":"United States","Website":"https:\/\/tang.eas.gatech.edu\/","Journal Name":"ACS Sustainable Resource Management","Last Name":"Tang","Institution Name":"Georgia Institute of Technology","Masthead Disclaimer":false},{"Email":"bruno.mattos@aalto.fi","First Name":"Bruno D.","Masthead Category":"Early Career Board","Country":"Finland","Website":"https:\/\/research.aalto.fi\/en\/persons\/bruno-dufau-mattos","Journal Name":"ACS Sustainable Resource Management","Last Name":"Mattos","Institution Name":"Aalto University","Masthead Disclaimer":false},{"Email":"muranaka@cheme.kyoto-u.ac.jp","First Name":"Yosuke","Masthead Category":"Early Career Board","Country":"Japan","Website":"http:\/\/www.cheme.kyoto-u.ac.jp\/8koza\/estaff5.html","Journal Name":"ACS Sustainable Resource Management","Last Name":"Muranka","Institution Name":"Kyoto University","Masthead Disclaimer":false}]}