{"data":[{"Email":"spad@iacs.res.in","First Name":"Ayan","Masthead Category":"Editorial Advisory Board","Country":"India","Website":"https:\/\/iacs.res.in\/athusers\/index.php?navid=0&userid=IACS0017","Journal Name":"The Journal of Physical Chemistry Letters","Last Name":"Datta","Institution Name":"Indian Association for the Cultivation of Science","Masthead Disclaimer":false},{"Email":"jianliupku@pku.edu.cn","First Name":"Jian","Masthead Category":"Editorial Advisory Board","Country":"China","Website":"http:\/\/jianliugroup.pku.edu.cn\/members.html","Journal Name":"The Journal of Physical Chemistry Letters","Last Name":"Liu","Institution Name":"Peking University","Masthead Disclaimer":false},{"Email":"cuk-office@jpclett.acs.org","First Name":"Tanja","Masthead Category":"Senior Editor","Country":"United States","Website":"https:\/\/www.colorado.edu\/lab\/cuk\/tanja-cuk","Journal Name":"The Journal of Physical Chemistry Letters","Last Name":"Cuk","Institution Name":"University of Colorado at Boulder","Masthead Disclaimer":false},{"Email":"chmlx@nus.edu.sg","First Name":"Xiaogang","Masthead Category":"Editorial Advisory Board","Country":"Singapore","Website":"https:\/\/liuxg.science.nus.edu.sg\/head\/","Journal Name":"The Journal of Physical Chemistry Letters","Last Name":"Liu","Institution Name":"National University of Singapore","Masthead Disclaimer":false},{"Email":"eic@jpclett.acs.org","First Name":"Gregory D.","Masthead Category":"Editor-in-Chief","Country":"United States","Website":"https:\/\/chemistry.princeton.edu\/faculty-research\/faculty\/gregory-scholes\/","Journal Name":"The Journal of Physical Chemistry Letters","Last Name":"Scholes","Institution Name":"Princeton University","Masthead Disclaimer":false},{"Email":"tahei@riken.jp","First Name":"Tahei","Masthead Category":"Editorial Advisory Board","Country":"Japan","Website":"https:\/\/www2.riken.jp\/lab\/spectroscopy\/tahara-e.html","Journal Name":"The Journal of Physical Chemistry Letters","Last Name":"Tahara","Institution Name":"RIKEN","Masthead Disclaimer":false},{"Email":"xiazg@scut.edu.cn","First Name":"Zhiguo","Masthead Category":"Editorial Advisory Board","Country":"China","Website":"http:\/\/www2.scut.edu.cn\/physics\/2021\/0312\/c13953a421511\/page.htm","Journal Name":"The Journal of Physical Chemistry Letters","Last Name":"Xia","Institution Name":"South China University of Technology","Masthead Disclaimer":false},{"Email":"zhong-office@jpclett.acs.org","First Name":"Haizheng","Masthead Category":"Executive Editor","Country":"China","Website":"https:\/\/pure.bit.edu.cn\/en\/persons\/haizheng-zhong","Journal Name":"The Journal of Physical Chemistry Letters","Last Name":"Zhong","Institution Name":"Beijing Institute of Technology","Masthead Disclaimer":false},{"Email":"zhang-office@jpclett.acs.org","First Name":"Jin Z.","Masthead Category":"Executive Editor","Country":"United States","Website":"https:\/\/www.chemistry.ucsc.edu\/faculty\/index.php?uid=zhang","Journal Name":"The Journal of Physical Chemistry Letters","Last Name":"Zhang","Institution Name":"University of California Santa Cruz","Masthead Disclaimer":false},{"Email":"bisquert-office@jpclett.acs.org","First Name":"Juan","Masthead Category":"Executive Editor","Country":"Spain","Website":"https:\/\/www.upv.es\/ficha-personal\/jbisquer","Journal Name":"The Journal of Physical Chemistry Letters","Last Name":"Bisquert","Institution Name":"Instituto de Tecnología Química (UPV-CSIC)","Masthead Disclaimer":false},{"Email":"prezhdo-office@jpclett.acs.org","First Name":"Oleg V.","Masthead Category":"Executive Editor","Country":"United States","Website":"https:\/\/chemistry.unm.edu\/people\/faculty\/profile\/oleg-prezhdo.html","Journal Name":"The Journal of Physical Chemistry Letters","Last Name":"Prezhdo","Institution Name":"University of New Mexico","Masthead Disclaimer":false},{"Email":"fu-office@jpclett.acs.org","First Name":"Qiang","Masthead Category":"Senior Editor","Country":"China","Website":"https:\/\/fruit.dicp.ac.cn\/info\/1016\/1270.htm","Journal Name":"The Journal of Physical Chemistry Letters","Last Name":"Fu","Institution Name":"Dalian Institute of Chemical Physics","Masthead Disclaimer":false},{"Email":"gssc@mit.edu","First Name":"Gabriela S.","Masthead Category":"Editorial Advisory Board","Country":"United States","Website":"http:\/\/www.schlaucohenlab.com","Journal Name":"The Journal of Physical Chemistry Letters","Last Name":"Schlau-Cohen","Institution Name":"Massachusetts Institute of Technology","Masthead Disclaimer":false},{"Email":"joelyuen@ucsd.edu","First Name":"Joel","Masthead Category":"Editorial Advisory Board","Country":"United States","Website":"http:\/\/yuenzhougroup.ucsd.edu\/","Journal Name":"The Journal of Physical Chemistry Letters","Last Name":"Yuen-Zhou","Institution Name":"University of California San Diego","Masthead Disclaimer":false},{"Email":"jlwang@seu.edu.cn","First Name":"Jinlan","Masthead Category":"Editorial Advisory Board","Country":"China","Website":"https:\/\/physics.seu.edu.cn\/jlwang\/","Journal Name":"The Journal of Physical Chemistry Letters","Last Name":"Wang","Institution Name":"Southeast University","Masthead Disclaimer":false},{"Email":"tsukuda-office@jpclett.acs.org","First Name":"Tatsuya","Masthead Category":"Senior Editor","Country":"Japan","Website":"https:\/\/tsukudalab.chem.s.u-tokyo.ac.jp\/index-e.html","Journal Name":"The Journal of Physical Chemistry Letters","Last Name":"Tsukuda","Institution Name":"University of Tokyo","Masthead Disclaimer":false},{"Email":"long-office@jpclett.acs.org","First Name":"Run","Masthead Category":"Senior Editor","Country":"China","Website":"http:\/\/www.chem.bnu.edu.cn\/szll\/jsdw\/llhwlhxyjs\/js3\/143154.html","Journal Name":"The Journal of Physical Chemistry Letters","Last Name":"Long","Institution Name":"Beijing Normal University","Masthead Disclaimer":false},{"Email":"jcaram@chem.ucla.edu","First Name":"Justin","Masthead Category":"Editorial Advisory Board","Country":"United States","Website":"https:\/\/caramlab.chem.ucla.edu\/","Journal Name":"The Journal of Physical Chemistry Letters","Last Name":"Caram","Institution Name":"University of California Los Angeles","Masthead Disclaimer":false},{"Email":"jc3972@columbia.edu","First Name":"Jingguang","Masthead Category":"Editorial Advisory Board","Country":"United States","Website":"http:\/\/blogs.cuit.columbia.edu\/chengroup\/","Journal Name":"The Journal of Physical Chemistry Letters","Last Name":"Chen","Institution Name":"Columbia University","Masthead Disclaimer":false},{"Email":"yfang@snnu.edu.cn","First Name":"Yu","Masthead Category":"Editorial Advisory Board","Country":"China","Website":"http:\/\/yfang.snnu.edu.cn\/","Journal Name":"The Journal of Physical Chemistry Letters","Last Name":"Fang","Institution Name":"Shaanxi Normal University","Masthead Disclaimer":false},{"Email":"habteyes@unm.edu","First Name":"Terefe","Masthead Category":"Editorial Advisory Board","Country":"United States","Website":"https:\/\/sites.google.com\/site\/tghabteyes","Journal Name":"The Journal of Physical Chemistry Letters","Last Name":"Habteyes","Institution Name":"University of New Mexico","Masthead Disclaimer":false},{"Email":"majing@nju.edu.cn","First Name":"Jing","Masthead Category":"Editorial Advisory Board","Country":"China","Website":"https:\/\/stuex.nju.edu.cn\/en_\/7e\/f3\/c23879a360179\/page.htm","Journal Name":"The Journal of Physical Chemistry Letters","Last Name":"Ma","Institution Name":"Nanjing University","Masthead Disclaimer":false},{"Email":"tada.mizuki.u6@f.mail.nagoya-u.ac.jp","First Name":"Mizuki","Masthead Category":"Editorial Advisory Board","Country":"Japan","Website":"https:\/\/cat.chem.nagoya-u.ac.jp\/member_tada_en.html","Journal Name":"The Journal of Physical Chemistry Letters","Last Name":"Tada","Institution Name":"Nagoya University","Masthead Disclaimer":false},{"Email":"elles@ku.edu","First Name":"Christopher G.","Masthead Category":"Editorial Advisory Board","Country":"United States","Website":"https:\/\/ellesgroup.ku.edu\/","Journal Name":"The Journal of Physical Chemistry Letters","Last Name":"Elles","Institution Name":"University of Kansas","Masthead Disclaimer":false},{"Email":"pat.kambhampati@mcgill.ca","First Name":"Patanjali","Masthead Category":"Editorial Advisory Board","Country":"Canada","Website":"www.kambhampati-group.mcgill.ca","Journal Name":"The Journal of Physical Chemistry Letters","Last Name":"Kambhampati","Institution Name":"McGill University","Masthead Disclaimer":false},{"Email":"kazuma@g.ecc.u-tokyo.ac.jp","First Name":"Emiko","Masthead Category":"Editorial Advisory Board","Country":"Japan","Website":"https:\/\/www.appchem.t.u-tokyo.ac.jp\/en\/lab\/kim\/","Journal Name":"The Journal of Physical Chemistry Letters","Last Name":"Kazuma","Institution Name":"University of Tokyo","Masthead Disclaimer":false},{"Email":"t.kirchartz@fz-juelich.de","First Name":"Thomas","Masthead Category":"Editorial Advisory Board","Country":"Germany","Website":"https:\/\/www.uni-due.de\/nst\/ma_thomaskirchartz_en.php","Journal Name":"The Journal of Physical Chemistry Letters","Last Name":"Kirchartz","Institution Name":"Julich Research Centre Institute of Energy and Climate Research","Masthead Disclaimer":false},{"Email":"flagugne@uwo.ca","First Name":"François","Masthead Category":"Editorial Advisory Board","Country":"Canada","Website":"https:\/\/www.uwo.ca\/chem\/people\/faculty\/lagugne.html","Journal Name":"The Journal of Physical Chemistry Letters","Last Name":"Lagugné-Labarthet","Institution Name":"University of Western Ontario","Masthead Disclaimer":false},{"Email":"dlimmer@berkeley.edu","First Name":"David","Masthead Category":"Editorial Advisory Board","Country":"United States","Website":"http:\/\/www.cchem.berkeley.edu\/dtlgrp\/","Journal Name":"The Journal of Physical Chemistry Letters","Last Name":"Limmer","Institution Name":"University of California Berkeley","Masthead Disclaimer":false},{"Email":"jovana.milic@unifr.ch","First Name":"Jovana","Masthead Category":"Editorial Advisory Board","Country":"Switzerland","Website":"https:\/\/www.ami.swiss\/en\/about-us\/contact\/people-a-z\/person.html?personid=900","Journal Name":"The Journal of Physical Chemistry Letters","Last Name":"Milic","Institution Name":"University of Fribourg","Masthead Disclaimer":false},{"Email":"wissam.saidi@netl.doe.gov","First Name":"Wissam","Masthead Category":"Editorial Advisory Board","Country":"United States","Website":"https:\/\/www.pqi.org\/people\/wissam-saidi","Journal Name":"The Journal of Physical Chemistry Letters","Last Name":"Saidi","Institution Name":"National Energy Technology Laboratory","Masthead Disclaimer":false},{"Email":"hu-office@jpclett.acs.org","First Name":"Bingwen","Masthead Category":"Senior Editor","Country":"China","Website":"https:\/\/faculty.ecnu.edu.cn\/_s41\/hbw_en\/main.psp","Journal Name":"The Journal of Physical Chemistry Letters","Last Name":"Hu","Institution Name":"East China Normal University","Masthead Disclaimer":false},{"Email":"magistrato-office@jpclett.acs.org","First Name":"Alessandra","Masthead Category":"Senior Editor","Country":"Italy","Website":"https:\/\/people.sissa.it\/~alema\/Introduction.html","Journal Name":"The Journal of Physical Chemistry Letters","Last Name":"Magistrato","Institution Name":"Consiglio Nazionale delle Ricerche","Masthead Disclaimer":false},{"Email":"jacquemin-office@jpclett.acs.org","First Name":"Denis","Masthead Category":"Senior Editor","Country":"France","Website":"https:\/\/www.univ-nantes.fr\/denis-jacquemin","Journal Name":"The Journal of Physical Chemistry Letters","Last Name":"Jacquemin","Institution Name":"University of Nantes","Masthead Disclaimer":false},{"Email":"xmyang@dicp.ac.cn","First Name":"Xueming","Masthead Category":"Editorial Advisory Board","Country":"China","Website":"https:\/\/people.ucas.ac.cn\/~yangxueming?language=en","Journal Name":"The Journal of Physical Chemistry Letters","Last Name":"Yang","Institution Name":"State Key Laboratory of Molecular Reaction Dynamics","Masthead Disclaimer":false},{"Email":"ar525@cam.ac.uk","First Name":"Akshay","Masthead Category":"Editorial Advisory Board","Country":"United Kingdom","Website":"https:\/\/www.phy.cam.ac.uk\/directory\/dr-akshay-rao","Journal Name":"The Journal of Physical Chemistry Letters","Last Name":"Rao","Institution Name":"University of Cambridge","Masthead Disclaimer":false},{"Email":"gbotton@mcmaster.ca","First Name":"Gianluigi A.","Masthead Category":"Editorial Advisory Board","Country":"Canada","Website":"https:\/\/experts.mcmaster.ca\/display\/gbotton","Journal Name":"The Journal of Physical Chemistry Letters","Last Name":"Botton","Institution Name":"McMaster University","Masthead Disclaimer":false},{"Email":"dgoswami@iitk.ac.in","First Name":"Debabrata","Masthead Category":"Editorial Advisory Board","Country":"India","Website":"https:\/\/www.iitk.ac.in\/celt\/main\/People\/Faculties\/goswami.html","Journal Name":"The Journal of Physical Chemistry Letters","Last Name":"Goswami","Institution Name":"Indian Institute of Technology Kanpur","Masthead Disclaimer":false},{"Email":"pradeep@iitm.ac.in","First Name":"Thalappil","Masthead Category":"Editorial Advisory Board","Country":"India","Website":"https:\/\/chem.iitm.ac.in\/faculty\/pradeep\/","Journal Name":"The Journal of Physical Chemistry Letters","Last Name":"Pradeep","Institution Name":"Indian Institute of Technology Madras","Masthead Disclaimer":false},{"Email":"elisabetta.collini@unipd.it","First Name":"Elisabetta","Masthead Category":"Editorial Advisory Board","Country":"Italy","Website":"www.chimica.unipd.it\/elisabetta.collini","Journal Name":"The Journal of Physical Chemistry Letters","Last Name":"Collini","Institution Name":"University of Padova","Masthead Disclaimer":false},{"Email":"kanemitu@scl.kyoto-u.ac.jp","First Name":"Yoshihiko","Masthead Category":"Editorial Advisory Board","Country":"Japan","Website":"https:\/\/www.scl.kyoto-u.ac.jp\/~opt-nano\/en\/index.html","Journal Name":"The Journal of Physical Chemistry Letters","Last Name":"Kanemitsu","Institution Name":"Kyoto University","Masthead Disclaimer":false},{"Email":"dw34@cam.ac.uk","First Name":"David J.","Masthead Category":"Editorial Advisory Board","Country":"United Kingdom","Website":"https:\/\/www.ch.cam.ac.uk\/person\/dw34","Journal Name":"The Journal of Physical Chemistry Letters","Last Name":"Wales","Institution Name":"University of Cambridge","Masthead Disclaimer":false},{"Email":"liangwz@xmu.edu.cn","First Name":"WanZhen","Masthead Category":"Editorial Advisory Board","Country":"China","Website":"https:\/\/chem.xmu.edu.cn\/en\/info\/1010\/1369.htm","Journal Name":"The Journal of Physical Chemistry Letters","Last Name":"Liang","Institution Name":"Xiamen University","Masthead Disclaimer":false},{"Email":"kaiwu@pku.edu.cn","First Name":"Kai","Masthead Category":"Editorial Advisory Board","Country":"China","Website":"https:\/\/www.chem.pku.edu.cn\/wukai\/people\/group_leader\/index.htm","Journal Name":"The Journal of Physical Chemistry Letters","Last Name":"Wu","Institution Name":"Peking University","Masthead Disclaimer":false},{"Email":"dneumark@berkeley.edu","First Name":"Daniel M.","Masthead Category":"Editorial Advisory Board","Country":"United States","Website":"https:\/\/chemistry.berkeley.edu\/faculty\/chem\/neumark","Journal Name":"The Journal of Physical Chemistry Letters","Last Name":"Neumark","Institution Name":"University of California Berkeley","Masthead Disclaimer":false},{"Email":"himansu@niser.ac.in","First Name":"Himansu Sekhar","Masthead Category":"Editorial Advisory Board","Country":"India","Website":"https:\/\/www.niser.ac.in\/profile\/himansu","Journal Name":"The Journal of Physical Chemistry Letters","Last Name":"Biswal","Institution Name":"National Institute of Science Education and Research (NISER) Bhubaneswar","Masthead Disclaimer":false},{"Email":"ebensee@unisa.ac.za","First Name":"Eno E.","Masthead Category":"Editorial Advisory Board","Country":"South Africa","Website":null,"Journal Name":"The Journal of Physical Chemistry Letters","Last Name":"Ebenso","Institution Name":"University of South Africa","Masthead Disclaimer":false},{"Email":"tak.kee@adelaide.edu.au","First Name":"Tak W.","Masthead Category":"Editorial Advisory Board","Country":"Australia","Website":"https:\/\/researchers.adelaide.edu.au\/profile\/tak.kee","Journal Name":"The Journal of Physical Chemistry Letters","Last Name":"Kee","Institution Name":"The University of Adelaide","Masthead Disclaimer":false},{"Email":"stacy.copp@uci.edu","First Name":"Stacy M.","Masthead Category":"Editorial Advisory Board","Country":"United States","Website":"http:\/\/copplab.eng.uci.edu\/","Journal Name":"The Journal of Physical Chemistry Letters","Last Name":"Copp","Institution Name":"University of California Irvine","Masthead Disclaimer":false},{"Email":"rsuprakas@csir.co.za","First Name":"Suprakas Sinha","Masthead Category":"Editorial Advisory Board","Country":"South Africa","Website":"https:\/\/pure.uj.ac.za\/en\/persons\/suprakas-sinha-ray","Journal Name":"The Journal of Physical Chemistry Letters","Last Name":"Ray","Institution Name":"Council for Scientific and Industrial Research","Masthead Disclaimer":false},{"Email":"haibo.ma@sdu.edu.cn","First Name":"Haibo","Masthead Category":"Editorial Advisory Board","Country":"China","Website":"https:\/\/faculty.sdu.edu.cn\/mahaibo1\/zh_CN\/index.htm","Journal Name":"The Journal of Physical Chemistry Letters","Last Name":"Ma","Institution Name":"Shandong University","Masthead Disclaimer":false},{"Email":"alvaro.munozc@uss.cl","First Name":"Alvaro","Masthead Category":"Editorial Advisory Board","Country":"Chile","Website":"http:\/\/www.amclab.cl","Journal Name":"The Journal of Physical Chemistry Letters","Last Name":"Muñoz-Castro","Institution Name":"Universidad San Sebastian","Masthead Disclaimer":false},{"Email":"dibyajyoti@mse.iitd.ac.in","First Name":"Dibyajyoti","Masthead Category":"Editorial Advisory Board","Country":"India","Website":"https:\/\/mse.iitd.ac.in\/faculty-profile\/19","Journal Name":"The Journal of Physical Chemistry Letters","Last Name":"Ghosh","Institution Name":"Indian Institute of Technology Delhi","Masthead Disclaimer":false},{"Email":"yizhengjin@zju.edu.cn","First Name":"Yizheng","Masthead Category":"Editorial Advisory Board","Country":"China","Website":"http:\/\/www.device-chemistry.cn\/home.php","Journal Name":"The Journal of Physical Chemistry Letters","Last Name":"Jin","Institution Name":"Zhejiang University","Masthead Disclaimer":false},{"Email":"pingliu3@bnl.gov","First Name":"Ping","Masthead Category":"Editorial Advisory Board","Country":"United States","Website":"https:\/\/www.bnl.gov\/staff\/pingliu3","Journal Name":"The Journal of Physical Chemistry Letters","Last Name":"Liu","Institution Name":"Brookhaven National Laboratory","Masthead Disclaimer":false},{"Email":"svetlana.kilina@ndsu.edu","First Name":"Svetlana V.","Masthead Category":"Editorial Advisory Board","Country":"United States","Website":"https:\/\/www.ndsu.edu\/chemistry\/people\/teaching_and_research_faculty\/svetlana_kilina\/","Journal Name":"The Journal of Physical Chemistry Letters","Last Name":"Kilina","Institution Name":"North Dakota State University","Masthead Disclaimer":false},{"Email":"loos@irsamc.ups-tlse.fr","First Name":"Pierre-Francois","Masthead Category":"Editorial Advisory Board","Country":"France","Website":"https:\/\/pfloos.github.io\/WEB_LOOS\/","Journal Name":"The Journal of Physical Chemistry Letters","Last Name":"Loos","Institution Name":"Université de Toulouse","Masthead Disclaimer":false},{"Email":"qipang@gxu.edu.cn","First Name":"Qi","Masthead Category":"Editorial Advisory Board","Country":"China","Website":null,"Journal Name":"The Journal of Physical Chemistry Letters","Last Name":"Pang","Institution Name":"Guangxi University","Masthead Disclaimer":false},{"Email":"pranab.sarka@gmail.com","First Name":"Pranab","Masthead Category":"Editorial Advisory Board","Country":"India","Website":"https:\/\/vbchem.ac.in\/PranabSarkar\/","Journal Name":"The Journal of Physical Chemistry Letters","Last Name":"Sarkar","Institution Name":"Visva-Bharati","Masthead Disclaimer":false},{"Email":"dtrivedi@clarkson.edu","First Name":"Dhara Jayshankar","Masthead Category":"Editorial Advisory Board","Country":"United States","Website":"https:\/\/www.clarkson.edu\/people\/dhara-trivedi","Journal Name":"The Journal of Physical Chemistry Letters","Last Name":"Trivedi","Institution Name":"Clarkson University","Masthead Disclaimer":false},{"Email":"andongxia@bupt.edu.cn","First Name":"Andong","Masthead Category":"Editorial Advisory Board","Country":"China","Website":"https:\/\/science.bupt.edu.cn\/info\/1118\/1604.htm","Journal Name":"The Journal of Physical Chemistry Letters","Last Name":"Xia","Institution Name":"Beijing University of Posts and Telecommunications","Masthead Disclaimer":false},{"Email":"zengrsh@guet.edu.cn","First Name":"Ruosheng","Masthead Category":"Editorial Advisory Board","Country":"China","Website":null,"Journal Name":"The Journal of Physical Chemistry Letters","Last Name":"Zeng","Institution Name":"Guangxi University","Masthead Disclaimer":false},{"Email":"patra-office@jpclett.acs.org","First Name":"Amitava","Masthead Category":"Senior Editor","Country":"India","Website":"http:\/\/iacs.res.in\/athusers\/index.php?navid=0&userid=IACS005#37632","Journal Name":"The Journal of Physical Chemistry Letters","Last Name":"Patra","Institution Name":"Indian Association for the Cultivation of Science","Masthead Disclaimer":false},{"Email":"managing.editor@jpclett.acs.org","First Name":"Joseph","Masthead Category":"Managing Editor","Country":"United States","Website":null,"Journal Name":"The Journal of Physical Chemistry Letters","Last Name":"Messinger","Institution Name":"American Chemical Society","Masthead Disclaimer":false},{"Email":"franco-office@jpclett.acs.org","First Name":"Ignacio","Masthead Category":"Senior Editor","Country":"United States","Website":"https:\/\/sas.rochester.edu\/chm\/groups\/franco\/","Journal Name":"The Journal of Physical Chemistry Letters","Last Name":"Franco","Institution Name":"University of Rochester","Masthead Disclaimer":false},{"Email":"pcossio@flatironinstitute.org","First Name":"Pilar","Masthead Category":"Editorial Advisory Board","Country":"United States","Website":"https:\/\/www.simonsfoundation.org\/people\/pilar-cossio\/","Journal Name":"The Journal of Physical Chemistry Letters","Last Name":"Cossio","Institution Name":"Flatiron Institute","Masthead Disclaimer":false},{"Email":"chenj@uark.edu","First Name":"Jingyi","Masthead Category":"Editorial Advisory Board","Country":"United States","Website":"https:\/\/chenj.hosted.uark.edu\/","Journal Name":"The Journal of Physical Chemistry Letters","Last Name":"Chen","Institution Name":"University of Arkansas Fayetteville","Masthead Disclaimer":false},{"Email":"mbird@bnl.gov","First Name":"Matthew","Masthead Category":"Editorial Advisory Board","Country":"United States","Website":"https:\/\/www.bnl.gov\/staff\/mbird","Journal Name":"The Journal of Physical Chemistry Letters","Last Name":"Bird","Institution Name":"Brookhaven National Laboratory","Masthead Disclaimer":false},{"Email":"gunnar.jeschke@phys.chem.ethz.ch","First Name":"Gunnar","Masthead Category":"Editorial Advisory Board","Country":"Switzerland","Website":"https:\/\/chab.ethz.ch\/en\/research\/faculty\/person-detail.gjeschke.html","Journal Name":"The Journal of Physical Chemistry Letters","Last Name":"Jeschke","Institution Name":"ETH Zurich","Masthead Disclaimer":false},{"Email":"cecilia.clementi@fu-berlin.de","First Name":"Cecilia","Masthead Category":"Editorial Advisory Board","Country":"Germany","Website":"http:\/\/www.physik.fu-berlin.de\/en\/einrichtungen\/ag\/ag-clementi","Journal Name":"The Journal of Physical Chemistry Letters","Last Name":"Clementi","Institution Name":"Free University of Berlin","Masthead Disclaimer":false},{"Email":"kouliangzhi@gmail.com","First Name":"Liangzhi","Masthead Category":"Editorial Advisory Board","Country":"Australia","Website":null,"Journal Name":"The Journal of Physical Chemistry Letters","Last Name":"Kou","Institution Name":"Queensland University of Technology","Masthead Disclaimer":false},{"Email":"g.colombo@unipv.it","First Name":"Giorgio","Masthead Category":"Editorial Advisory Board","Country":"Italy","Website":"https:\/\/colombolab.wordpress.com\/giorgio-colombo\/","Journal Name":"The Journal of Physical Chemistry Letters","Last Name":"Colombo","Institution Name":"University of Pavia","Masthead Disclaimer":false},{"Email":"zdenek.dohnalek@pnnl.gov","First Name":"Zdenek","Masthead Category":"Editorial Advisory Board","Country":"United States","Website":"https:\/\/www.pnnl.gov\/people\/zdenek-dohnalek","Journal Name":"The Journal of Physical Chemistry Letters","Last Name":"Dohnalek","Institution Name":"Pacific Northwest National Laboratory","Masthead Disclaimer":false},{"Email":"tkarmakar@chemistry.iitd.ac.in","First Name":"Tarak","Masthead Category":"Editorial Advisory Board","Country":"India","Website":"https:\/\/sites.google.com\/view\/tarakkchem","Journal Name":"The Journal of Physical Chemistry Letters","Last Name":"Karmakar","Institution Name":"Indian Institute of Technology","Masthead Disclaimer":false},{"Email":"antonio.monari@u-paris.fr","First Name":"Antonio","Masthead Category":"Editorial Advisory Board","Country":"France","Website":"https:\/\/orcid.org\/0000-0001-9464-1463","Journal Name":"The Journal of Physical Chemistry Letters","Last Name":"Monari","Institution Name":"Université de Paris","Masthead Disclaimer":false},{"Email":"may1@ornl.gov","First Name":"Ying-Zhong","Masthead Category":"Editorial Advisory Board","Country":"United States","Website":"https:\/\/www.ornl.gov\/sites\/default\/files\/2024-05\/CV_Yingzhong%20Ma%2005212024.pdf","Journal Name":"The Journal of Physical Chemistry Letters","Last Name":"Ma","Institution Name":"Oak Ridge National Laboratory","Masthead Disclaimer":false},{"Email":"xunchengsu@nankai.edu.cn","First Name":"Xun-Cheng","Masthead Category":"Editorial Advisory Board","Country":"China","Website":"https:\/\/chemen.nankai.edu.cn\/2021\/0629\/c24618a379121\/page.htm","Journal Name":"The Journal of Physical Chemistry Letters","Last Name":"Su","Institution Name":"Nankai University","Masthead Disclaimer":false},{"Email":"zhuxi@cuhk.edu.cn","First Name":"Xi","Masthead Category":"Editorial Advisory Board","Country":"China","Website":"https:\/\/polysz.cuhk.edu.cn\/en\/content\/10895","Journal Name":"The Journal of Physical Chemistry Letters","Last Name":"Zhu","Institution Name":"The Chinese University of Hong Kong","Masthead Disclaimer":false},{"Email":"nnair@iitk.ac.in","First Name":"Nisanth","Masthead Category":"Editorial Advisory Board","Country":"India","Website":"https:\/\/www.iitk.ac.in\/nisanth-n-nair","Journal Name":"The Journal of Physical Chemistry Letters","Last Name":"Nair","Institution Name":"Indian Institute of Technology Kanpur","Masthead Disclaimer":false},{"Email":"weichman@princeton.edu","First Name":"Marissa","Masthead Category":"Editorial Advisory Board","Country":"United States","Website":"https:\/\/chemistry.princeton.edu\/faculty-research\/faculty\/marissa-weichman\/","Journal Name":"The Journal of Physical Chemistry Letters","Last Name":"Weichman","Institution Name":"Princeton University","Masthead Disclaimer":false},{"Email":"qjuan@mail.tsinghua.edu.cn","First Name":"Juan","Masthead Category":"Editorial Advisory Board","Country":"China","Website":"https:\/\/www.chem.tsinghua.edu.cn\/chemen\/info\/1051\/1551.htm","Journal Name":"The Journal of Physical Chemistry Letters","Last Name":"Qiao","Institution Name":"Tsinghua University","Masthead Disclaimer":false},{"Email":"jphyschm@chem.ucla.edu","First Name":"Benjamin","Masthead Category":"Editorial Advisory Board","Country":"United States","Website":"http:\/\/www.chem.ucla.edu\/dept\/Faculty\/schwartz\/index.html","Journal Name":"The Journal of Physical Chemistry Letters","Last Name":"Schwartz","Institution Name":"University of California Los Angeles","Masthead Disclaimer":false},{"Email":"shijying@mail.sysu.edu.cn","First Name":"Jian-Ying","Masthead Category":"Editorial Advisory Board","Country":"China","Website":"https:\/\/ce.sysu.edu.cn\/zh-hans\/teacher\/695","Journal Name":"The Journal of Physical Chemistry Letters","Last Name":"Shi","Institution Name":"Sun Yat-sen University","Masthead Disclaimer":false},{"Email":"jfzhu@ustc.edu.cn","First Name":"Junfa","Masthead Category":"Editorial Advisory Board","Country":"China","Website":"http:\/\/surfchem.ustc.edu.cn\/","Journal Name":"The Journal of Physical Chemistry Letters","Last Name":"Zhu","Institution Name":"University of Science and Technology of China","Masthead Disclaimer":false},{"Email":"ana@chem.ucla.edu","First Name":"Anastassia N.","Masthead Category":"Editorial Advisory Board","Country":"United States","Website":"https:\/\/www.chem.ucla.edu\/~ana\/members.html","Journal Name":"The Journal of Physical Chemistry Letters","Last Name":"Alexandrova","Institution Name":"University of California Los Angeles","Masthead Disclaimer":false}]}