{"data":[{"Email":"m.edirisinghe@ucl.ac.uk","First Name":"Mohan","Masthead Category":"Editorial Advisory Board","Country":"United Kingdom","Website":"https:\/\/www.edirisinghelab.com\/","Journal Name":"Langmuir","Last Name":"Edirisinghe","Institution Name":"University College London","Masthead Disclaimer":false},{"Email":"almeidap@uncw.edu","First Name":"Paulo F.","Masthead Category":"Editorial Advisory Board","Country":"United States","Website":"https:\/\/people.uncw.edu\/almeidap\/","Journal Name":"Langmuir","Last Name":"Almeida","Institution Name":"University of North Carolina","Masthead Disclaimer":false},{"Email":"sbent@stanford.edu","First Name":"Stacey F.","Masthead Category":"Editorial Advisory Board","Country":"United States","Website":"http:\/\/bentgroup.stanford.edu","Journal Name":"Langmuir","Last Name":"Bent","Institution Name":"Stanford University","Masthead Disclaimer":false},{"Email":"psc11@psu.edu","First Name":"Paul S.","Masthead Category":"Editorial Advisory Board","Country":"United States","Website":"https:\/\/sites.psu.edu\/cremer\/","Journal Name":"Langmuir","Last Name":"Cremer","Institution Name":"Pennsylvania State University","Masthead Disclaimer":false},{"Email":"liujw@uwaterloo.ca","First Name":"Juewen","Masthead Category":"Editorial Advisory Board","Country":"Canada","Website":"https:\/\/uwaterloo.ca\/chemistry\/profile\/liujw","Journal Name":"Langmuir","Last Name":"Liu","Institution Name":"University of Waterloo","Masthead Disclaimer":false},{"Email":"schmitt@crpp-bordeaux.cnrs.fr","First Name":"Véronique","Masthead Category":"Editorial Advisory Board","Country":"France","Website":"https:\/\/scholar.google.com\/citations?hl=fr&user=ssUjN70AAAAJ&view_op=list_works&sortby=pubdate","Journal Name":"Langmuir","Last Name":"Schmitt","Institution Name":"CNRS","Masthead Disclaimer":false},{"Email":"esmith1@iastate.edu","First Name":"Emily","Masthead Category":"Editorial Advisory Board","Country":"United States","Website":"https:\/\/www.chem.iastate.edu\/people\/emily-smith","Journal Name":"Langmuir","Last Name":"Smith","Institution Name":"Iowa State University","Masthead Disclaimer":false},{"Email":"andrewt@udel.edu","First Name":"Andrew V.","Masthead Category":"Editorial Advisory Board","Country":"United States","Website":"http:\/\/www1.udel.edu\/chem\/teplyakov\/main.htm","Journal Name":"Langmuir","Last Name":"Teplyakov","Institution Name":"University of Delaware","Masthead Disclaimer":false},{"Email":"hongbo.zeng@ualberta.ca","First Name":"Hongbo","Masthead Category":"Editorial Advisory Board","Country":"Canada","Website":"https:\/\/sites.ualberta.ca\/~hzeng2\/index.html","Journal Name":"Langmuir","Last Name":"Zeng","Institution Name":"University of Alberta","Masthead Disclaimer":false},{"Email":"zhangwk@jlu.edu.cn","First Name":"Wenke","Masthead Category":"Editorial Advisory Board","Country":"China","Website":"https:\/\/supramol.jlu.edu.cn\/info\/1097\/1437.htm","Journal Name":"Langmuir","Last Name":"Zhang","Institution Name":"Jilin University","Masthead Disclaimer":false},{"Email":"msgzzhang@scut.edu.cn","First Name":"Guangzhao","Masthead Category":"Editorial Advisory Board","Country":"China","Website":"http:\/\/www2.scut.edu.cn\/materials_en\/2019\/1011\/c23549a339172\/page.htm","Journal Name":"Langmuir","Last Name":"Zhang","Institution Name":"South China University of Technology","Masthead Disclaimer":false},{"Email":"njcho@ntu.edu.sg","First Name":"Nam-Joon","Masthead Category":"Editorial Advisory Board","Country":"Singapore","Website":"https:\/\/www.namjooncho.com","Journal Name":"Langmuir","Last Name":"Cho","Institution Name":"Nanyang Technological University","Masthead Disclaimer":false},{"Email":"tongai@cuhk.edu.hk","First Name":"To","Masthead Category":"Editorial Advisory Board","Country":"China","Website":"http:\/\/www.cuhk.edu.hk\/research\/NgaiToGroup\/people.html","Journal Name":"Langmuir","Last Name":"Ngai","Institution Name":"The Chinese University of Hong Kong","Masthead Disclaimer":false},{"Email":"chen-office@langmuir.acs.org","First Name":"Zhan","Masthead Category":"Senior Editor","Country":"United States","Website":"http:\/\/www.umich.edu\/~chenlab\/","Journal Name":"Langmuir","Last Name":"Chen","Institution Name":"University of Michigan","Masthead Disclaimer":false},{"Email":"hao-office@langmuir.acs.org","First Name":"Jingcheng","Masthead Category":"Senior Editor","Country":"China","Website":"http:\/\/cis.sdu.edu.cn\/info\/1023\/1088.htm","Journal Name":"Langmuir","Last Name":"Hao","Institution Name":"Shandong University","Masthead Disclaimer":false},{"Email":"jduhamel@uwaterloo.ca","First Name":"Jean","Masthead Category":"Editorial Advisory Board","Country":"Canada","Website":"https:\/\/uwaterloo.ca\/chemistry\/people-profiles\/jean-duhamel","Journal Name":"Langmuir","Last Name":"Duhamel","Institution Name":"University of Waterloo","Masthead Disclaimer":false},{"Email":"janet.elliott@ualberta.ca","First Name":"Janet A. W.","Masthead Category":"Editorial Advisory Board","Country":"Canada","Website":"https:\/\/apps.ualberta.ca\/directory\/person\/jawe","Journal Name":"Langmuir","Last Name":"Elliott","Institution Name":"University of Alberta","Masthead Disclaimer":false},{"Email":"hisakai@rs.noda.tus.ac.jp","First Name":"Hideki","Masthead Category":"Editorial Advisory Board","Country":"Japan","Website":"https:\/\/www.tus.ac.jp\/en\/fac\/p\/index.php?21f8","Journal Name":"Langmuir","Last Name":"Sakai","Institution Name":"Tokyo University of Science","Masthead Disclaimer":false},{"Email":"jinwoongkim@skku.edu","First Name":"Jin Woong","Masthead Category":"Editorial Advisory Board","Country":"Republic of Korea","Website":"https:\/\/cheme.skku.edu\/kim-jin-woong\/","Journal Name":"Langmuir","Last Name":"Kim","Institution Name":"Sungkyunkwan University","Masthead Disclaimer":false},{"Email":"ylyu@fudan.edu.cn","First Name":"Yanlei","Masthead Category":"Editorial Advisory Board","Country":"China","Website":"https:\/\/lcpolymergroup.fudan.edu.cn","Journal Name":"Langmuir","Last Name":"Yu","Institution Name":"Fudan University","Masthead Disclaimer":false},{"Email":"yusa@eng.u-hyogo.ac.jp","First Name":"Shin-ichi","Masthead Category":"Editorial Advisory Board","Country":"Japan","Website":"http:\/\/www.eng.u-hyogo.ac.jp\/msc\/yusa\/index.html","Journal Name":"Langmuir","Last Name":"Yusa","Institution Name":"University of Hyogo","Masthead Disclaimer":false},{"Email":"eic@langmuir.acs.org","First Name":"Gilbert C.","Masthead Category":"Editor-in-Chief","Country":"Canada","Website":"https:\/\/www.thewalkerlab.com\/","Journal Name":"Langmuir","Last Name":"Walker","Institution Name":"University of Toronto","Masthead Disclaimer":false},{"Email":"s.j.a.debeer@utwente.nl","First Name":"Sissi","Masthead Category":"Editorial Advisory Board","Country":"Netherlands","Website":"https:\/\/people.utwente.nl\/s.j.a.debeer?tab=contact","Journal Name":"Langmuir","Last Name":"de Beer","Institution Name":"Universiteit Twente","Masthead Disclaimer":false},{"Email":"shan.zou@nrc-cnrc.gc.ca","First Name":"Shan","Masthead Category":"Editorial Advisory Board","Country":"Canada","Website":"http:\/\/shan-nrc.weebly.com\/","Journal Name":"Langmuir","Last Name":"Zou","Institution Name":"National Research Council","Masthead Disclaimer":false},{"Email":"wang-office@langmuir.acs.org","First Name":"Yilin","Masthead Category":"Senior Editor","Country":"China","Website":"http:\/\/yilinwang.iccas.ac.cn\/","Journal Name":"Langmuir","Last Name":"Wang","Institution Name":"Institute of Chemistry Chinese Academy of Sciences","Masthead Disclaimer":false},{"Email":"joshi-office@langmuir.acs.org","First Name":"Yogesh M.","Masthead Category":"Senior Editor","Country":"India","Website":"http:\/\/home.iitk.ac.in\/~joshi\/","Journal Name":"Langmuir","Last Name":"Joshi","Institution Name":"Indian Institute of Technology Kanpur","Masthead Disclaimer":false},{"Email":"tsao-office@langmuir.acs.org","First Name":"Heng-Kwong","Masthead Category":"Senior Editor","Country":"Taiwan","Website":"https:\/\/scholars.ncu.edu.tw\/en\/persons\/heng-kwong-tsao","Journal Name":"Langmuir","Last Name":"Tsao","Institution Name":"National Central University","Masthead Disclaimer":false},{"Email":"gang.zheng@uhnres.utoronto.ca","First Name":"Gang","Masthead Category":"Editorial Advisory Board","Country":"Canada","Website":"http:\/\/zhenglab.utoronto.ca\/","Journal Name":"Langmuir","Last Name":"Zheng","Institution Name":"University of Toronto","Masthead Disclaimer":false},{"Email":"pieterc@mail.ubc.ca","First Name":"Pieter","Masthead Category":"Editorial Advisory Board","Country":"Canada","Website":"http:\/\/www.liposomes.ca","Journal Name":"Langmuir","Last Name":"Cullis","Institution Name":"University of British Columbia","Masthead Disclaimer":false},{"Email":"heinz-office@langmuir.acs.org","First Name":"Hendrik","Masthead Category":"Senior Editor","Country":"United States","Website":"https:\/\/bionanostructures.com\/","Journal Name":"Langmuir","Last Name":"Heinz","Institution Name":"University of Colorado at Boulder","Masthead Disclaimer":false},{"Email":"chaudhury-office@langmuir.acs.org","First Name":"Manoj","Masthead Category":"Senior Editor","Country":"United States","Website":"https:\/\/www.lehigh.edu\/~mkc4\/","Journal Name":"Langmuir","Last Name":"Chaudhury","Institution Name":"Lehigh University","Masthead Disclaimer":false},{"Email":"cranston-office@langmuir.acs.org","First Name":"Emily D.","Masthead Category":"Senior Editor","Country":"Canada","Website":"https:\/\/cranstongroup.forestry.ubc.ca\/","Journal Name":"Langmuir","Last Name":"Cranston","Institution Name":"University of British Columbia","Masthead Disclaimer":false},{"Email":"xgx214@lehigh.edu","First Name":"Xiaoji","Masthead Category":"Editorial Advisory Board","Country":"United States","Website":"https:\/\/sites.google.com\/view\/xiaojixu","Journal Name":"Langmuir","Last Name":"Xu","Institution Name":"Lehigh University","Masthead Disclaimer":false},{"Email":"oheinz-office@langmuir.acs.org","First Name":"Ozge","Masthead Category":"Perspectives Editor","Country":"United States","Website":"https:\/\/profiles.ucdenver.edu\/display\/36453832","Journal Name":"Langmuir","Last Name":"Heinz","Institution Name":"University of Colorado at Denver","Masthead Disclaimer":false},{"Email":"ypwang-office@langmuir.acs.org","First Name":"Yapei","Masthead Category":"Senior Editor","Country":"China","Website":"https:\/\/clr.ruc.edu.cn\/En\/Teacher_Hom\/Yapei_Wang\/index.htm","Journal Name":"Langmuir","Last Name":"Wang","Institution Name":"Renmin University of China","Masthead Disclaimer":false},{"Email":"kariske@unifesp.br","First Name":"Karin A.","Masthead Category":"Editorial Advisory Board","Country":"Brazil","Website":"https:\/\/sp.unifesp.br\/epm\/biofisica\/graduacao\/epm\/equipe\/menu-docente#karin-do-amaral-riske","Journal Name":"Langmuir","Last Name":"Riske","Institution Name":"Federal University of Sao Paulo","Masthead Disclaimer":false},{"Email":"basa@iitm.ac.in","First Name":"Madivala G.","Masthead Category":"Editorial Advisory Board","Country":"India","Website":"https:\/\/che.iitm.ac.in\/basa\/","Journal Name":"Langmuir","Last Name":"Basavaraj","Institution Name":"Indian Institute of Technology Madras","Masthead Disclaimer":false},{"Email":"mcnamee.cathy.8r@kyoto-u.ac.jp","First Name":"Cathy E.","Masthead Category":"Editorial Advisory Board","Country":"Japan","Website":"https:\/\/kdb.iimc.kyoto-u.ac.jp\/profile_private\/en.ef53f795402bcd92.html","Journal Name":"Langmuir","Last Name":"McNamee","Institution Name":"Kyoto University","Masthead Disclaimer":false},{"Email":"chjitkangl@usm.my","First Name":"JitKang","Masthead Category":"Editorial Advisory Board","Country":"Malaysia","Website":"https:\/\/www.andrew.cmu.edu\/user\/jitkangl\/Index.htm","Journal Name":"Langmuir","Last Name":"Lim","Institution Name":"Universiti Sains Malaysia","Masthead Disclaimer":false},{"Email":"boinovich@mail.ru","First Name":"Ludmila B.","Masthead Category":"Editorial Advisory Board","Country":"Russian Federation","Website":"https:\/\/scholar.google.com\/citations?hl=en&user=mPxI9LcAAAAJ&view_op=list_works&sortby=pubdate","Journal Name":"Langmuir","Last Name":"Boinovich","Institution Name":"Frumkin Institute of Physical Chemistry and Electrochemistry RAS","Masthead Disclaimer":false},{"Email":"christine.dewolf@concordia.ca","First Name":"Christine E.","Masthead Category":"Editorial Advisory Board","Country":"Canada","Website":"https:\/\/www.concordia.ca\/faculty\/christine-dewolf.html","Journal Name":"Langmuir","Last Name":"DeWolf","Institution Name":"Concordia University","Masthead Disclaimer":false},{"Email":"chiara.neto@sydney.edu.au","First Name":"Chiara","Masthead Category":"Editorial Advisory Board","Country":"Australia","Website":"https:\/\/neto.sydney.edu.au\/","Journal Name":"Langmuir","Last Name":"Neto","Institution Name":"The University of Sydney","Masthead Disclaimer":false},{"Email":"karen.edler@chem.lu.se","First Name":"Karen J.","Masthead Category":"Editorial Advisory Board","Country":"Sweden","Website":"https:\/\/portal.research.lu.se\/en\/persons\/karen-edler","Journal Name":"Langmuir","Last Name":"Edler","Institution Name":"Lund University","Masthead Disclaimer":false},{"Email":"yxfan@iccas.ac.cn","First Name":"Yaxun","Masthead Category":"Editorial Advisory Board","Country":"China","Website":"http:\/\/yilinwang.iccas.ac.cn\/132","Journal Name":"Langmuir","Last Name":"Fan","Institution Name":"Institute of Chemistry Chinese Academy of Sciences","Masthead Disclaimer":false},{"Email":"xgong@whut.edu.cn","First Name":"Xiao","Masthead Category":"Editorial Advisory Board","Country":"China","Website":"http:\/\/silicate.whut.edu.cn\/rcdw\/kyry\/201911\/t20191121_422202.shtml","Journal Name":"Langmuir","Last Name":"Gong","Institution Name":"Wuhan University of Technology","Masthead Disclaimer":false},{"Email":"helm@uni-greifswald.de","First Name":"Christiane A.","Masthead Category":"Editorial Advisory Board","Country":"Germany","Website":"https:\/\/physik.uni-greifswald.de\/ag-helm\/","Journal Name":"Langmuir","Last Name":"Helm","Institution Name":"University of Greifswald","Masthead Disclaimer":false},{"Email":"zuanwang@polyu.edu.hk","First Name":"Zuankai","Masthead Category":"Editorial Advisory Board","Country":"China","Website":"https:\/\/wangzuankai.wixsite.com\/wanglab","Journal Name":"Langmuir","Last Name":"Wang","Institution Name":"The Hong Kong Polytechnic University","Masthead Disclaimer":false},{"Email":"wuxiaomin@mail.tsinghua.edu.cn","First Name":"Xiaomin","Masthead Category":"Editorial Advisory Board","Country":"China","Website":"https:\/\/tsinghua.xmxugroup.com","Journal Name":"Langmuir","Last Name":"Wu","Institution Name":"Tsinghua University","Masthead Disclaimer":false},{"Email":"mse_yangp@ujn.edu.cn","First Name":"Ping","Masthead Category":"Editorial Advisory Board","Country":"China","Website":"http:\/\/mse.ujn.edu.cn\/info\/1206\/6148.htm","Journal Name":"Langmuir","Last Name":"Yang","Institution Name":"University of Jinan","Masthead Disclaimer":false},{"Email":"yfzhou@sjtu.edu.cn","First Name":"Yongfeng","Masthead Category":"Editorial Advisory Board","Country":"China","Website":"https:\/\/yfzhou.sjtu.edu.cn\/En","Journal Name":"Langmuir","Last Name":"Zhou","Institution Name":"Shanghai Jiao Tong University","Masthead Disclaimer":false},{"Email":"hong-office@langmuir.acs.org","First Name":"Wenjing","Masthead Category":"Senior Editor","Country":"China","Website":"https:\/\/pilab.xmu.edu.cn\/","Journal Name":"Langmuir","Last Name":"Hong","Institution Name":"Xiamen University","Masthead Disclaimer":false},{"Email":"koos-office@langmuir.acs.org","First Name":"Erin","Masthead Category":"Senior Editor","Country":"Belgium","Website":"https:\/\/cit.kuleuven.be\/smart\/people\/00109273","Journal Name":"Langmuir","Last Name":"Koos","Institution Name":"KU Leuven","Masthead Disclaimer":false},{"Email":"ruiwen@iccas.ac.cn","First Name":"Rui","Masthead Category":"Editorial Advisory Board","Country":"China","Website":"http:\/\/mnn.iccas.ac.cn\/wenrui\/","Journal Name":"Langmuir","Last Name":"Wen","Institution Name":"Institute of Chemistry Chinese Academy of Sciences","Masthead Disclaimer":false},{"Email":"vhgrassian@ucsd.edu","First Name":"Vicki H.","Masthead Category":"Editorial Advisory Board","Country":"United States","Website":"https:\/\/sites.google.com\/ucsd.edu\/grassiangroup\/","Journal Name":"Langmuir","Last Name":"Grassian","Institution Name":"University of California San Diego","Masthead Disclaimer":false},{"Email":"nilmoni@chem.iitkgp.ac.in","First Name":"Nilmoni","Masthead Category":"Editorial Advisory Board","Country":"India","Website":"http:\/\/www.chemistry.iitkgp.ac.in\/professor\/nilmoni","Journal Name":"Langmuir","Last Name":"Sarkar","Institution Name":"Indian Institute of Technology Kharagpur","Masthead Disclaimer":false},{"Email":"v.kaneti@uq.edu.au","First Name":"Yusuf Valentino","Masthead Category":"Editorial Advisory Board","Country":"Australia","Website":"https:\/\/researchers.uq.edu.au\/researcher\/29830","Journal Name":"Langmuir","Last Name":"Kaneti","Institution Name":"The University of Queensland","Masthead Disclaimer":false},{"Email":"tsemrick@mail.pse.umass.edu","First Name":"Todd","Masthead Category":"Editorial Advisory Board","Country":"United States","Website":"https:\/\/www.pse.umass.edu\/faculty\/researchgroup\/emrick\/research","Journal Name":"Langmuir","Last Name":"Emrick","Institution Name":"University of Massachusetts Amherst","Masthead Disclaimer":false},{"Email":"santore@mail.pse.umass.edu","First Name":"Maria M.","Masthead Category":"Editorial Advisory Board","Country":"United States","Website":"https:\/\/www.pse.umass.edu\/faculty\/researchgroup\/santore","Journal Name":"Langmuir","Last Name":"Santore","Institution Name":"University of Massachusetts Amherst","Masthead Disclaimer":false},{"Email":"drygchung@gmail.com","First Name":"Yongchul G.","Masthead Category":"Editorial Advisory Board","Country":"Republic of Korea","Website":"https:\/\/sites.google.com\/view\/mtap-lab","Journal Name":"Langmuir","Last Name":"Chung","Institution Name":"Pusan National University","Masthead Disclaimer":false},{"Email":"ksahu@che.iith.ac.in","First Name":"Kirti Chandra","Masthead Category":"Editorial Advisory Board","Country":"India","Website":"https:\/\/people.iith.ac.in\/ksahu\/","Journal Name":"Langmuir","Last Name":"Sahu","Institution Name":"Indian Institute of Technology Hyderabad","Masthead Disclaimer":false},{"Email":"d_suzuki@shinshu-u.ac.jp","First Name":"Daisuke","Masthead Category":"Editorial Advisory Board","Country":"Japan","Website":"https:\/\/suzuki-particle.com\/","Journal Name":"Langmuir","Last Name":"Suzuki","Institution Name":"Okayama University","Masthead Disclaimer":false},{"Email":"ma-office@langmuir.acs.org","First Name":"Jing","Masthead Category":"Senior Editor","Country":"China","Website":"https:\/\/stuex.nju.edu.cn\/en_\/7e\/f3\/c23879a360179\/page.htm","Journal Name":"Langmuir","Last Name":"Ma","Institution Name":"Nanjing University","Masthead Disclaimer":false},{"Email":"managing.editor@langmuir.acs.org","First Name":"Greco González","Masthead Category":"Managing Editor","Country":"United States","Website":null,"Journal Name":"Langmuir","Last Name":"Miera","Institution Name":"American Chemical Society","Masthead Disclaimer":false},{"Email":"lilian_hsiao@ncsu.edu","First Name":"Lilian C.","Masthead Category":"Early Career Board","Country":"United States","Website":"www.hsiaolab.com","Journal Name":"Langmuir","Last Name":"Hsiao","Institution Name":"North Carolina State University","Masthead Disclaimer":false},{"Email":"g.bolognesi@ucl.ac.uk","First Name":"Guido","Masthead Category":"Early Career Board","Country":"United Kingdom","Website":"www.particlemicrofluidics.com\/ucl","Journal Name":"Langmuir","Last Name":"Bolognesi","Institution Name":"University College London","Masthead Disclaimer":false},{"Email":"jdriske@ilstu.edu","First Name":"Jeremy D.","Masthead Category":"Editorial Advisory Board","Country":"United States","Website":"https:\/\/chemistry.illinoisstate.edu\/faculty-staff\/profile\/?ulid=jdriske","Journal Name":"Langmuir","Last Name":"Driskell","Institution Name":"Illinois State University","Masthead Disclaimer":false},{"Email":"jianliupku@pku.edu.cn","First Name":"Jian","Masthead Category":"Editorial Advisory Board","Country":"China","Website":"http:\/\/jianliugroup.pku.edu.cn","Journal Name":"Langmuir","Last Name":"Liu","Institution Name":"Peking University","Masthead Disclaimer":false},{"Email":"pbazazi@mines.edu","First Name":"Parisa","Masthead Category":"Early Career Board","Country":"United States","Website":"https:\/\/petroleum.mines.edu\/project\/bazazi-parisa","Journal Name":"Langmuir","Last Name":"Bazazi","Institution Name":"Colorado School of Mines","Masthead Disclaimer":false},{"Email":"hjqian@jlu.edu.cn","First Name":"Hu-Jun","Masthead Category":"Editorial Advisory Board","Country":"China","Website":"https:\/\/supramol.jlu.edu.cn\/info\/1097\/1432.htm","Journal Name":"Langmuir","Last Name":"Qian","Institution Name":"Jilin University","Masthead Disclaimer":false},{"Email":"prerna@iisc.ac.in","First Name":"Prerna","Masthead Category":"Early Career Board","Country":"India","Website":"https:\/\/sites.google.com\/site\/biocolloids\/","Journal Name":"Langmuir","Last Name":"Sharma","Institution Name":"Indian Institute of Science, Bengaluru","Masthead Disclaimer":false},{"Email":"rfoudazi@ou.edu","First Name":"Reza","Masthead Category":"Editorial Advisory Board","Country":"United States","Website":"https:\/\/foudazi-lab.com\/","Journal Name":"Langmuir","Last Name":"Foudazi","Institution Name":"University of Oklahoma","Masthead Disclaimer":false},{"Email":"rkatsumata@umass.edu","First Name":"Reika","Masthead Category":"Editorial Advisory Board","Country":"United States","Website":"https:\/\/katsumata4.wixsite.com\/home","Journal Name":"Langmuir","Last Name":"Katsumata","Institution Name":"University of Massachusetts Amherst","Masthead Disclaimer":false},{"Email":"lel55@pitt.edu","First Name":"Lei","Masthead Category":"Editorial Advisory Board","Country":"United States","Website":"http:\/\/www.engineering.pitt.edu\/Sub-Sites\/Labs\/Li_Lab\/Li-Lab-Index\/","Journal Name":"Langmuir","Last Name":"Li","Institution Name":"University of Pittsburgh","Masthead Disclaimer":false},{"Email":"liubing@iccas.ac.cn","First Name":"Bing","Masthead Category":"Editorial Advisory Board","Country":"China","Website":"http:\/\/liubing.iccas.ac.cn\/","Journal Name":"Langmuir","Last Name":"Liu","Institution Name":"Institute of Chemistry, Chinese Academy of Sciences","Masthead Disclaimer":false},{"Email":"marina_ruths@uml.edu","First Name":"Marina","Masthead Category":"Editorial Advisory Board","Country":"United States","Website":"https:\/\/www.uml.edu\/sciences\/chemistry\/people\/ruths-marina.aspx","Journal Name":"Langmuir","Last Name":"Ruths","Institution Name":"University of Massachusetts Lowell","Masthead Disclaimer":false},{"Email":"p.spicer@unsw.edu.au","First Name":"Patrick","Masthead Category":"Editorial Advisory Board","Country":"Australia","Website":"https:\/\/nonequilibrium.com\/","Journal Name":"Langmuir","Last Name":"Spicer","Institution Name":"UNSW Sydney","Masthead Disclaimer":false},{"Email":"lvelarde@buffalo.edu","First Name":"Luis","Masthead Category":"Editorial Advisory Board","Country":"United States","Website":"https:\/\/ubwp.buffalo.edu\/velardelab\/","Journal Name":"Langmuir","Last Name":"Velarde","Institution Name":"University at Buffalo","Masthead Disclaimer":false},{"Email":"rosenkranz-office@langmuir.acs.org","First Name":"Andreas","Masthead Category":"Senior Editor","Country":"Chile","Website":"https:\/\/laboratoriodetribologia.cl\/en\/about-us\/","Journal Name":"Langmuir","Last Name":"Rosenkranz","Institution Name":"Universidad de Chile","Masthead Disclaimer":false},{"Email":"ardona-office@langmuir.acs.org","First Name":"Herdeline Ann","Masthead Category":"Senior Editor","Country":"United States","Website":"ardonalabs.com","Journal Name":"Langmuir","Last Name":"Ardoña","Institution Name":"University of California Irvine","Masthead Disclaimer":false},{"Email":"jeong-office@langmuir.acs.org","First Name":"Nak Cheon","Masthead Category":"Senior Editor","Country":"Republic of Korea","Website":"https:\/\/www.nclab.dgist.ac.kr","Journal Name":"Langmuir","Last Name":"Jeong","Institution Name":"Daegu Gyeongbuk Institute of Science and Technology","Masthead Disclaimer":false},{"Email":"murphycj@illinois.edu","First Name":"Catherine J.","Masthead Category":"Editorial Advisory Board","Country":"United States","Website":"https:\/\/chemistry.illinois.edu\/murphycj","Journal Name":"Langmuir","Last Name":"Murphy","Institution Name":"University of Illinois at Urbana-Champaign","Masthead Disclaimer":false},{"Email":"nutt@mpip-mainz.mpg.de","First Name":"Hans-Juergen","Masthead Category":"Editorial Advisory Board","Country":"Germany","Website":"https:\/\/www.mpip-mainz.mpg.de\/en\/butt\/director","Journal Name":"Langmuir","Last Name":"Butt","Institution Name":"Max Planck Institute for Polymer Research","Masthead Disclaimer":false},{"Email":"baglioni@csgi.unifi.it","First Name":"Piero","Masthead Category":"Editorial Advisory Board","Country":"Italy","Website":"https:\/\/www.csgi.unifi.it\/person.php?p=28","Journal Name":"Langmuir","Last Name":"Baglioni","Institution Name":"University of Florence","Masthead Disclaimer":false},{"Email":"jbhuang@pku.edu.cn","First Name":"Jianbin","Masthead Category":"Editorial Advisory Board","Country":"China","Website":"https:\/\/www.chem.pku.edu.cn\/huangjb\/en\/index.htm","Journal Name":"Langmuir","Last Name":"Huang","Institution Name":"Peking University","Masthead Disclaimer":false},{"Email":"mulvaney@unimelb.edu.au","First Name":"Paul","Masthead Category":"Editorial Advisory Board","Country":"Australia","Website":"https:\/\/www.nanoparticle.com","Journal Name":"Langmuir","Last Name":"Mulvaney","Institution Name":"University of Melbourne","Masthead Disclaimer":false},{"Email":"jiang-office@langmuir.acs.org","First Name":"Shaoyi","Masthead Category":"Senior Editor","Country":"United States","Website":"http:\/\/jgroup.bme.cornell.edu\/index.html","Journal Name":"Langmuir","Last Name":"Jiang","Institution Name":"Cornell University","Masthead Disclaimer":false},{"Email":"furst@udel.edu","First Name":"Eric M.","Masthead Category":"Editorial Advisory Board","Country":"United States","Website":"http:\/\/lem.che.udel.edu\/wiki\/index.php?n=Main.Welcome","Journal Name":"Langmuir","Last Name":"Furst","Institution Name":"University of Delaware","Masthead Disclaimer":false},{"Email":"hastone@princeton.edu","First Name":"Howard A.","Masthead Category":"Editorial Advisory Board","Country":"United States","Website":"https:\/\/stonelab.princeton.edu","Journal Name":"Langmuir","Last Name":"Stone","Institution Name":"Princeton University","Masthead Disclaimer":false},{"Email":"jfrechette@berkeley.edu","First Name":"Joelle","Masthead Category":"Editorial Advisory Board","Country":"United States","Website":"https:\/\/frechettelab.com\/","Journal Name":"Langmuir","Last Name":"Frechette","Institution Name":"University of California Berkeley","Masthead Disclaimer":false},{"Email":"takahara-office@langmuir.acs.org","First Name":"Atsushi","Masthead Category":"Senior Editor","Country":"Japan","Website":"http:\/\/takahara.ifoc.kyushu-u.ac.jp\/","Journal Name":"Langmuir","Last Name":"Takahara","Institution Name":"Kyushu University","Masthead Disclaimer":false},{"Email":"s.fujii@chem.oit.ac.jp","First Name":"Syuji","Masthead Category":"Editorial Advisory Board","Country":"Japan","Website":"https:\/\/www.chem.oit.ac.jp\/en\/research\/member\/lab-apm","Journal Name":"Langmuir","Last Name":"Fujii","Institution Name":"Osaka Institute of Technology","Masthead Disclaimer":false}]}